gronpy/__main__.py
gronpy/__version__.py
gronpy/gron.py
gronpy/ungron.py
gronpy-1.0.0.dist-info/METADATA
gronpy-1.0.0.dist-info/WHEEL
gronpy-1.0.0.dist-info/entry_points.txt
gronpy-1.0.0.dist-info/RECORD
