Metadata-Version: 2.3
Name: gronpy
Version: 1.0.0
Summary: A Python port of `gron`
Author: Adam McKay
Author-email: adam@beepboop.digital
Requires-Python: >=3.10,<3.12
Classifier: Programming Language :: Python :: 3
Classifier: Programming Language :: Python :: 3.10
Classifier: Programming Language :: Python :: 3.11
Requires-Dist: fake-useragent (>=2.0.3,<3.0.0)
Requires-Dist: httpx (>=0.25,<0.29)
Requires-Dist: js2py (>=0.74,<0.75)
Requires-Dist: rich (>=13.6.0,<14.0.0)
Requires-Dist: typer (>=0.9,<0.16)
